auto_query_cluster/__init__.py
auto_query_cluster/optics.py
auto_query_cluster/query_cluster.py
auto_query_cluster/demo/queries.txt
auto_query_cluster/sent2vec.models/config.json
auto_query_cluster/sent2vec.models/sent_similarity_model.pt
auto_query_cluster-0.0.2.0.dist-info/METADATA
auto_query_cluster-0.0.2.0.dist-info/WHEEL
auto_query_cluster-0.0.2.0.dist-info/top_level.txt
auto_query_cluster-0.0.2.0.dist-info/RECORD
