Metadata-Version: 2.1
Name: auto-query-cluster
Version: 0.0.2.0
Summary: Auto Query Cluster
Home-page: https://gitee.com/fubo_linux/auto_query_cluster
Author: fubo
Author-email: fb_linux@163.com
License: UNKNOWN
Platform: UNKNOWN
Classifier: Programming Language :: Python :: 3
Classifier: License :: OSI Approved :: MIT License
Classifier: Operating System :: OS Independent
Requires-Python: >=3.6
Requires-Dist: nlp-nn (>=0.0.3.0)
Requires-Dist: sklearn
